<?xml version="1.0" encoding="UTF-8" standalone="yes"?>
<PTSDownsampler>
	<TimeSeries>
		<sourceAddress>dpaw.data.bom.idy.manjimup.raw</sourceAddress>
		<destinationAddress>dpaw.data.bom.idy.manjimup.downsampled.12hr</destinationAddress>
		<sensorsFile>config/resources/data/bom/idy/manjimup/sensors.xml</sensorsFile>
		<startDate>IDY_MANJIMUP_DATAPROCESSING-START@timeline</startDate>
		<endDate>IDY_MANJIMUP_DATAPROCESSING-END@timeline</endDate>
		<processingTimestep>43200</processingTimestep>
	</TimeSeries>
</PTSDownsampler>
