<?xml version="1.0" encoding="UTF-8" standalone="yes"?>
<ARMSContextFile>
	<ARMSContextConfig>
		<address>data.dow.walyunga</address>
		<resourceType>Station</resourceType>
		<fileName>config/resources/data/dow/walyunga/station.xml</fileName>
	</ARMSContextConfig>

	<ARMSContextConfig>
		<address>data.dow.anacondadrive_616092</address>
		<resourceType>Station</resourceType>
		<fileName>config/resources/data/dow/anacondadrive/station.xml</fileName>
	</ARMSContextConfig>
	<ARMSContextConfig>
		<address>data.dow.benararoad_616084</address>
		<resourceType>Station</resourceType>
		<fileName>config/resources/data/dow/benararoad/station.xml</fileName>
	</ARMSContextConfig>
	<ARMSContextConfig>
		<address>data.dow.doghill_614030</address>
		<resourceType>Station</resourceType>
		<fileName>config/resources/data/dow/doghill/station.xml</fileName>
	</ARMSContextConfig>
	<ARMSContextConfig>
		<address>data.dow.forresthighway_613036</address>
		<resourceType>Station</resourceType>
		<fileName>config/resources/data/dow/forresthighway/station.xml</fileName>
	</ARMSContextConfig>
	<ARMSContextConfig>
		<address>data.dow.gtnorthanhwbridge_616088</address>
		<resourceType>Station</resourceType>
		<fileName>config/resources/data/dow/gtnorthanhwbridge/station.xml</fileName>
	</ARMSContextConfig>
	<ARMSContextConfig>
		<address>data.dow.gullroad_614120</address>
		<resourceType>Station</resourceType>
		<fileName>config/resources/data/dow/gullroad/station.xml</fileName>
	</ARMSContextConfig>
	<ARMSContextConfig>
		<address>data.dow.karnup_614121</address>
		<resourceType>Station</resourceType>
		<fileName>config/resources/data/dow/karnuproad/station.xml</fileName>
	</ARMSContextConfig>
	<ARMSContextConfig>
		<address>data.dow.kielman_614063</address>
		<resourceType>Station</resourceType>
		<fileName>config/resources/data/dow/kielman/station.xml</fileName>
	</ARMSContextConfig>
	<ARMSContextConfig>
		<address>data.dow.nationalpark_616178</address>
		<resourceType>Station</resourceType>
		<fileName>config/resources/data/dow/nationalpark/station.xml</fileName>
	</ARMSContextConfig>
	<ARMSContextConfig>
		<address>data.dow.oldbunburyroad_613031</address>
		<resourceType>Station</resourceType>
		<fileName>config/resources/data/dow/oldbunburyrd/station.xml</fileName>
	</ARMSContextConfig>
	<ARMSContextConfig>
		<address>data.dow.pinjarra_614065</address>
		<resourceType>Station</resourceType>
		<fileName>config/resources/data/dow/pinjarra/station.xml</fileName>
	</ARMSContextConfig>
	<ARMSContextConfig>
		<address>data.dow.riverroad_616099</address>
		<resourceType>Station</resourceType>
		<fileName>config/resources/data/dow/riverroad/station.xml</fileName>
	</ARMSContextConfig>
	<ARMSContextConfig>
		<address>data.dow.railwayparade_616189</address>
		<resourceType>Station</resourceType>
		<fileName>config/resources/data/dow/railwayparade/station.xml</fileName>
	</ARMSContextConfig>
	<ARMSContextConfig>
		<address>data.dow.seaforth_616027</address>
		<resourceType>Station</resourceType>
		<fileName>config/resources/data/dow/seaforth/station.xml</fileName>
	</ARMSContextConfig>
	<ARMSContextConfig>
		<address>data.dow.sladestreet_616082</address>
		<resourceType>Station</resourceType>
		<fileName>config/resources/data/dow/seaforth/station.xml</fileName>
	</ARMSContextConfig>
	<ARMSContextConfig>
		<address>data.dow.whitemanroad_616086</address>
		<resourceType>Station</resourceType>
		<fileName>config/resources/data/dow/whitemanroad/station.xml</fileName>
	</ARMSContextConfig>
	<ARMSContextConfig>
		<address>data.dow.yackaboon_613027</address>
		<resourceType>Station</resourceType>
		<fileName>config/resources/data/dow/yackaboon/station.xml</fileName>
	</ARMSContextConfig>
</ARMSContextFile>
